datadumb/__init__.py
datadumb/backends/__init__.py
datadumb/backends/base.py
datadumb/backends/pandas_adapter.py
datadumb/backends/polars_adapter.py
datadumb/core/__init__.py
datadumb/core/exceptions.py
datadumb/core/interfaces.py
datadumb/core/models.py
datadumb/core/orchestrator.py
datadumb/detection/__init__.py
datadumb/detection/format_detector.py
datadumb/detection/parameter_inferrer.py
datadumb/py.typed
datadumb/utils/__init__.py
datadumb/utils/logging.py
datadumb-0.1.0.dist-info/WHEEL
datadumb-0.1.0.dist-info/METADATA
datadumb-0.1.0.dist-info/RECORD
