Metadata-Version: 2.3
Name: datadumb
Version: 0.1.0
Summary: Smart data loader with automatic format detection and parameter inference for pandas and polars
Keywords: data,loading,pandas,polars,csv,excel,parquet,automatic,detection
Author: Joscha Bisping
Author-email: Joscha Bisping <joscha.l.bisping@tu-berlin.de>
License: MIT
Classifier: Development Status :: 4 - Beta
Classifier: Intended Audience :: Developers
Classifier: Intended Audience :: Science/Research
Classifier: License :: OSI Approved :: MIT License
Classifier: Operating System :: OS Independent
Classifier: Programming Language :: Python :: 3
Classifier: Programming Language :: Python :: 3.11
Classifier: Programming Language :: Python :: 3.12
Classifier: Programming Language :: Python :: 3.13
Classifier: Topic :: Scientific/Engineering
Classifier: Topic :: Software Development :: Libraries :: Python Modules
Classifier: Topic :: Utilities
Requires-Dist: fastexcel>=0.18.0
Requires-Dist: openpyxl>=3.1.5
Requires-Dist: pandas>=2.3.3
Requires-Dist: polars>=1.36.1
Requires-Dist: xlrd>=2.0.2
Requires-Dist: xlwt>=1.3.0
Requires-Dist: pandas>=1.0.0 ; extra == 'all'
Requires-Dist: polars>=0.18.0 ; extra == 'all'
Requires-Dist: openpyxl>=3.0.0 ; extra == 'all'
Requires-Dist: xlrd>=2.0.0 ; extra == 'all'
Requires-Dist: openpyxl>=3.0.0 ; extra == 'excel'
Requires-Dist: xlrd>=2.0.0 ; extra == 'excel'
Requires-Dist: pandas>=1.0.0 ; extra == 'pandas'
Requires-Dist: polars>=0.18.0 ; extra == 'polars'
Requires-Python: >=3.11
Project-URL: Homepage, https://github.com/jlb-jlb/datadumb
Project-URL: Issues, https://github.com/jlb-jlb/datadumb/issues
Project-URL: Repository, https://github.com/jlb-jlb/datadumb
Provides-Extra: all
Provides-Extra: excel
Provides-Extra: pandas
Provides-Extra: polars
